finpack/.coveragerc
finpack/__init__.py
finpack/core/__init__.py
finpack/core/cli.py
finpack/core/exceptions.py
finpack/core/init.py
finpack/core/loader.py
finpack/core/models.py
finpack/reports/__init__.py
finpack/reports/allocation.py
finpack/reports/balsheet.py
finpack/reports/cashflow.py
finpack/utils.py
finpack-0.2.3.dist-info/entry_points.txt
finpack-0.2.3.dist-info/LICENSE
finpack-0.2.3.dist-info/WHEEL
finpack-0.2.3.dist-info/METADATA
finpack-0.2.3.dist-info/RECORD
