Metadata-Version: 2.1
Name: finpack
Version: 0.2.3
Summary: Super simple financial tracking.
Home-page: https://github.com/RackReaver/FinPack
License: Apache-2.0
Keywords: python,personal-finance,finance,financial,personal-finances,balance-sheet,personal-finance-manager,cashflow-management
Author: rackreaver
Author-email: rackreaver@gmail.com
Requires-Python: >=3.9,<4.0
Classifier: License :: OSI Approved :: Apache Software License
Classifier: Programming Language :: Python :: 3
Classifier: Programming Language :: Python :: 3.10
Classifier: Programming Language :: Python :: 3.9
Requires-Dist: docopt (>=0.6.2,<0.7.0)
Project-URL: Repository, https://github.com/RackReaver/FinPack
